{
  "schema": "bizra-execution-receipt-v1",
  "receipt_type": "Execution",
  "hardware_anchor": "fc095b726fdba80dfdc8ad303f22b3e917aae3bf989b2fbeb3ec35872847c8ab",
  "receipt_id": "EXEC-20260112215257-000001",
  "timestamp": "2026-01-12T21:52:57.226753169Z",
  "task_summary": "Implement feature toggle system",
  "sat_validation_ms": 92,
  "pat_execution_ms": 34,
  "total_latency_ms": 132,
  "synergy_score": 0.9216221345122904,
  "ihsan_score": 0.9271892034448683,
  "ihsan_threshold": 0.8,
  "pat_agents_count": 8,
  "sat_approvers_count": 6,
  "harberger_tax": 0.0001,
  "integrity_hash": "sha256:b179be2bd78884b0a7b9ceda7b992946bc2b5462053f221be3d954ed34c6e14c"
}